quipcell/__init__.py
quipcell/_maxent_dual_lbfgs.py
quipcell/_quipcell.py
quipcell/_solvers.py
quipcell-0.8.dist-info/LICENSE.txt
quipcell-0.8.dist-info/METADATA
quipcell-0.8.dist-info/WHEEL
quipcell-0.8.dist-info/top_level.txt
quipcell-0.8.dist-info/RECORD
