Metadata-Version: 2.1
Name: quipcell
Version: 0.8
Summary: Fine-scale cellular deconvolution based on Generalized Cross Entropy
Home-page: https://github.com/genentech/quipcell
Author: Jack Kamm
Author-email: jackkamm@gmail.com
License: MIT
Project-URL: Source, https://github.com/genentech/quipcell/
Platform: any
Classifier: Development Status :: 4 - Beta
Classifier: Programming Language :: Python
License-File: LICENSE.txt
Requires-Dist: numpy
Requires-Dist: scipy
Requires-Dist: pandas
Requires-Dist: scikit-learn
Requires-Dist: cvxpy
Requires-Dist: jax
Requires-Dist: jaxlib
Requires-Dist: importlib-metadata ; python_version >= "3.8"
Provides-Extra: testing
Requires-Dist: setuptools ; extra == 'testing'
Requires-Dist: pytest ; extra == 'testing'
Requires-Dist: pytest-cov ; extra == 'testing'
